{
 "race_id": "202607232015060406",
 "name": "Ｃ２三四五",
 "venue": "大井",
 "race_no": 6,
 "post_time": "17:30",
 "horses": [
  {
   "num": 1,
   "name": "シャークウォーニン"
  },
  {
   "num": 2,
   "name": "トーアナカヨシ"
  },
  {
   "num": 3,
   "name": "グランダイト"
  },
  {
   "num": 4,
   "name": "ヨシノローズ"
  },
  {
   "num": 5,
   "name": "シタベッド"
  },
  {
   "num": 6,
   "name": "スズノハマヤ"
  },
  {
   "num": 7,
   "name": "リュウノウィザード"
  },
  {
   "num": 8,
   "name": "フェルメール"
  },
  {
   "num": 9,
   "name": "ピンナダ"
  },
  {
   "num": 10,
   "name": "ファーストフォルテ"
  },
  {
   "num": 11,
   "name": "サントレッダー"
  },
  {
   "num": 12,
   "name": "ボラボラフレイバー"
  },
  {
   "num": 13,
   "name": "イトウ"
  },
  {
   "num": 14,
   "name": "フラグランツァ"
  }
 ],
 "snapshots": [
  {
   "time": "17:30",
   "odds": [
    52.4,
    33.9,
    1.6,
    148.8,
    17.0,
    9.9,
    185.5,
    11.7,
    26.7,
    45.6,
    142.3,
    15.7,
    63.7,
    4.8
   ]
  }
 ]
}